aiobooru/__init__.py
aiobooru/booru.py
aiobooru-0.1.3.dist-info/LICENSE
aiobooru-0.1.3.dist-info/METADATA
aiobooru-0.1.3.dist-info/WHEEL
aiobooru-0.1.3.dist-info/top_level.txt
aiobooru-0.1.3.dist-info/RECORD
