Metadata-Version: 2.1
Name: aiobooru
Version: 0.1.3
Summary: A danbooru API helper using aiohttp
Home-page: https://github.com/YuiYukihira/aiobooru
Author: Yui Yukihira
Author-email: yuiyukihira1@gmail.com
License: MIT
Platform: UNKNOWN
Classifier: Programming Language :: Python :: 3
Classifier: License :: OSI Approved :: MIT License
Classifier: Operating System :: OS Independent
Requires-Python: >=3.7.0
Requires-Dist: aiohttp (>=3.5.4)
Provides-Extra: aiofiles
Requires-Dist: aiofiles ; extra == 'aiofiles'
